Workbook

Sheet How to use
A1: Free purchase order template from The Gantry (gantry.work)
A3: 1. Open this file in Google Sheets: File > Import > Upload, or open it from Google Drive.
A4: 2. Add your suppliers on the Suppliers tab. The supplier email fills itself in on the POs tab.
A5: 3. On the POs tab, fill in the white columns. Grey columns (PO No, email, amounts, totals) are formulas: do not type over them.
A6: 4. When a PO is ready to go, set Status to Ready. The Make scenario in the guide then creates the PO document, emails the PDF to the supplier and sets Status to Sent.
A7: 5. Filter by Status to see open orders. Do not sort the POs tab: PO numbers come from the row number.
A9: Full setup guide: https://www.gantry.work/p/purchase-order-template-google-sheets
A10: Stuck? https://tools.gantry.work/automation-help/?from=po-template

Sheet POs
A1: PO No | B1: Date | C1: Supplier | D1: Supplier email | E1: Deliver to | F1: Needed by | G1: Item 1 | H1: Qty 1 | I1: Price 1 | J1: Amount 1 | K1: Item 2 | L1: Qty 2 | M1: Price 2 | N1: Amount 2 | O1: Item 3 | P1: Qty 3 | Q1: Price 3 | R1: Amount 3 | S1: Subtotal | T1: GST | U1: Total | V1: Requested by | W1: Status | X1: PO document | Y1: Sent on
A2: =IF(C2="","","PO-"&TEXT(ROW()-1,"0000")) | B2: 2026-10-20 | C2: Bright Packaging | D2: =IF(C2="","",IFERROR(VLOOKUP(C2,Suppliers!A:B,2,FALSE),"")) | E2: Main warehouse, 12 Example Road | F2: 2026-10-27 | G2: Carton box 40x30x30 | H2: 200 | I2: 1.85 | J2: =IF(OR(H2="",I2=""),"",ROUND(H2*I2,2)) | K2: Packing tape 48mm | L2: 50 | M2: 2.4 | N2: =IF(OR(L2="",M2=""),"",ROUND(L2*M2,2)) | R2: =IF(OR(P2="",Q2=""),"",ROUND(P2*Q2,2)) | S2: =IF(C2="","",SUM(J2,N2,R2)) | T2: =IF(C2="","",ROUND(S2*Settings!$B$2,2)) | U2: =IF(C2="","",S2+T2) | V2: Mei Ling | W2: Ready
A3: =IF(C3="","","PO-"&TEXT(ROW()-1,"0000")) | B3: 2026-10-21 | C3: Harbour Supplies | D3: =IF(C3="","",IFERROR(VLOOKUP(C3,Suppliers!A:B,2,FALSE),"")) | E3: Main warehouse, 12 Example Road | F3: 2026-10-30 | G3: Pallet wrap 500mm | H3: 24 | I3: 14.5 | J3: =IF(OR(H3="",I3=""),"",ROUND(H3*I3,2)) | N3: =IF(OR(L3="",M3=""),"",ROUND(L3*M3,2)) | R3: =IF(OR(P3="",Q3=""),"",ROUND(P3*Q3,2)) | S3: =IF(C3="","",SUM(J3,N3,R3)) | T3: =IF(C3="","",ROUND(S3*Settings!$B$2,2)) | U3: =IF(C3="","",S3+T3) | V3: Mei Ling | W3: Draft
A4: =IF(C4="","","PO-"&TEXT(ROW()-1,"0000")) | D4: =IF(C4="","",IFERROR(VLOOKUP(C4,Suppliers!A:B,2,FALSE),"")) | J4: =IF(OR(H4="",I4=""),"",ROUND(H4*I4,2)) | N4: =IF(OR(L4="",M4=""),"",ROUND(L4*M4,2)) | R4: =IF(OR(P4="",Q4=""),"",ROUND(P4*Q4,2)) | S4: =IF(C4="","",SUM(J4,N4,R4)) | T4: =IF(C4="","",ROUND(S4*Settings!$B$2,2)) | U4: =IF(C4="","",S4+T4)
A5: =IF(C5="","","PO-"&TEXT(ROW()-1,"0000")) | D5: =IF(C5="","",IFERROR(VLOOKUP(C5,Suppliers!A:B,2,FALSE),"")) | J5: =IF(OR(H5="",I5=""),"",ROUND(H5*I5,2)) | N5: =IF(OR(L5="",M5=""),"",ROUND(L5*M5,2)) | R5: =IF(OR(P5="",Q5=""),"",ROUND(P5*Q5,2)) | S5: =IF(C5="","",SUM(J5,N5,R5)) | T5: =IF(C5="","",ROUND(S5*Settings!$B$2,2)) | U5: =IF(C5="","",S5+T5)
A6: =IF(C6="","","PO-"&TEXT(ROW()-1,"0000")) | D6: =IF(C6="","",IFERROR(VLOOKUP(C6,Suppliers!A:B,2,FALSE),"")) | J6: =IF(OR(H6="",I6=""),"",ROUND(H6*I6,2)) | N6: =IF(OR(L6="",M6=""),"",ROUND(L6*M6,2)) | R6: =IF(OR(P6="",Q6=""),"",ROUND(P6*Q6,2)) | S6: =IF(C6="","",SUM(J6,N6,R6)) | T6: =IF(C6="","",ROUND(S6*Settings!$B$2,2)) | U6: =IF(C6="","",S6+T6)
A7: =IF(C7="","","PO-"&TEXT(ROW()-1,"0000")) | D7: =IF(C7="","",IFERROR(VLOOKUP(C7,Suppliers!A:B,2,FALSE),"")) | J7: =IF(OR(H7="",I7=""),"",ROUND(H7*I7,2)) | N7: =IF(OR(L7="",M7=""),"",ROUND(L7*M7,2)) | R7: =IF(OR(P7="",Q7=""),"",ROUND(P7*Q7,2)) | S7: =IF(C7="","",SUM(J7,N7,R7)) | T7: =IF(C7="","",ROUND(S7*Settings!$B$2,2)) | U7: =IF(C7="","",S7+T7)
A8: =IF(C8="","","PO-"&TEXT(ROW()-1,"0000")) | D8: =IF(C8="","",IFERROR(VLOOKUP(C8,Suppliers!A:B,2,FALSE),"")) | J8: =IF(OR(H8="",I8=""),"",ROUND(H8*I8,2)) | N8: =IF(OR(L8="",M8=""),"",ROUND(L8*M8,2)) | R8: =IF(OR(P8="",Q8=""),"",ROUND(P8*Q8,2)) | S8: =IF(C8="","",SUM(J8,N8,R8)) | T8: =IF(C8="","",ROUND(S8*Settings!$B$2,2)) | U8: =IF(C8="","",S8+T8)
A9: =IF(C9="","","PO-"&TEXT(ROW()-1,"0000")) | D9: =IF(C9="","",IFERROR(VLOOKUP(C9,Suppliers!A:B,2,FALSE),"")) | J9: =IF(OR(H9="",I9=""),"",ROUND(H9*I9,2)) | N9: =IF(OR(L9="",M9=""),"",ROUND(L9*M9,2)) | R9: =IF(OR(P9="",Q9=""),"",ROUND(P9*Q9,2)) | S9: =IF(C9="","",SUM(J9,N9,R9)) | T9: =IF(C9="","",ROUND(S9*Settings!$B$2,2)) | U9: =IF(C9="","",S9+T9)
A10: =IF(C10="","","PO-"&TEXT(ROW()-1,"0000")) | D10: =IF(C10="","",IFERROR(VLOOKUP(C10,Suppliers!A:B,2,FALSE),"")) | J10: =IF(OR(H10="",I10=""),"",ROUND(H10*I10,2)) | N10: =IF(OR(L10="",M10=""),"",ROUND(L10*M10,2)) | R10: =IF(OR(P10="",Q10=""),"",ROUND(P10*Q10,2)) | S10: =IF(C10="","",SUM(J10,N10,R10)) | T10: =IF(C10="","",ROUND(S10*Settings!$B$2,2)) | U10: =IF(C10="","",S10+T10)
A11: =IF(C11="","","PO-"&TEXT(ROW()-1,"0000")) | D11: =IF(C11="","",IFERROR(VLOOKUP(C11,Suppliers!A:B,2,FALSE),"")) | J11: =IF(OR(H11="",I11=""),"",ROUND(H11*I11,2)) | N11: =IF(OR(L11="",M11=""),"",ROUND(L11*M11,2)) | R11: =IF(OR(P11="",Q11=""),"",ROUND(P11*Q11,2)) | S11: =IF(C11="","",SUM(J11,N11,R11)) | T11: =IF(C11="","",ROUND(S11*Settings!$B$2,2)) | U11: =IF(C11="","",S11+T11)
A12: =IF(C12="","","PO-"&TEXT(ROW()-1,"0000")) | D12: =IF(C12="","",IFERROR(VLOOKUP(C12,Suppliers!A:B,2,FALSE),"")) | J12: =IF(OR(H12="",I12=""),"",ROUND(H12*I12,2)) | N12: =IF(OR(L12="",M12=""),"",ROUND(L12*M12,2)) | R12: =IF(OR(P12="",Q12=""),"",ROUND(P12*Q12,2)) | S12: =IF(C12="","",SUM(J12,N12,R12)) | T12: =IF(C12="","",ROUND(S12*Settings!$B$2,2)) | U12: =IF(C12="","",S12+T12)
A13: =IF(C13="","","PO-"&TEXT(ROW()-1,"0000")) | D13: =IF(C13="","",IFERROR(VLOOKUP(C13,Suppliers!A:B,2,FALSE),"")) | J13: =IF(OR(H13="",I13=""),"",ROUND(H13*I13,2)) | N13: =IF(OR(L13="",M13=""),"",ROUND(L13*M13,2)) | R13: =IF(OR(P13="",Q13=""),"",ROUND(P13*Q13,2)) | S13: =IF(C13="","",SUM(J13,N13,R13)) | T13: =IF(C13="","",ROUND(S13*Settings!$B$2,2)) | U13: =IF(C13="","",S13+T13)
A14: =IF(C14="","","PO-"&TEXT(ROW()-1,"0000")) | D14: =IF(C14="","",IFERROR(VLOOKUP(C14,Suppliers!A:B,2,FALSE),"")) | J14: =IF(OR(H14="",I14=""),"",ROUND(H14*I14,2)) | N14: =IF(OR(L14="",M14=""),"",ROUND(L14*M14,2)) | R14: =IF(OR(P14="",Q14=""),"",ROUND(P14*Q14,2)) | S14: =IF(C14="","",SUM(J14,N14,R14)) | T14: =IF(C14="","",ROUND(S14*Settings!$B$2,2)) | U14: =IF(C14="","",S14+T14)
A15: =IF(C15="","","PO-"&TEXT(ROW()-1,"0000")) | D15: =IF(C15="","",IFERROR(VLOOKUP(C15,Suppliers!A:B,2,FALSE),"")) | J15: =IF(OR(H15="",I15=""),"",ROUND(H15*I15,2)) | N15: =IF(OR(L15="",M15=""),"",ROUND(L15*M15,2)) | R15: =IF(OR(P15="",Q15=""),"",ROUND(P15*Q15,2)) | S15: =IF(C15="","",SUM(J15,N15,R15)) | T15: =IF(C15="","",ROUND(S15*Settings!$B$2,2)) | U15: =IF(C15="","",S15+T15)
... A201: =IF(C201="","","PO-"&TEXT(ROW()-1,"0000")) | D201: =IF(C201="","",IFERROR(VLOOKUP(C201,Suppliers!A:B,2,FALSE),"")) | J201: =IF(OR(H201="",I201=""),"",ROUND(H201*I201,2)) | N201: =IF(OR(L201="",M201=""),"",ROUND(L201*M201,2)) | R201: =IF(OR(P201="",Q201=""),"",ROUND(P201*Q201,2)) | S201: =IF(C201="","",SUM(J201,N201,R201)) | T201: =IF(C201="","",ROUND(S201*Settings!$B$2,2)) | U201: =IF(C201="","",S201+T201)

Sheet Suppliers
A1: Supplier | B1: Email | C1: Payment terms | D1: Currency
A2: Bright Packaging | B2: orders@example.com | C2: 30 days | D2: SGD
A3: Harbour Supplies | B3: sales@example.com | C3: 14 days | D3: SGD

Sheet Settings
A1: Setting | B1: Value | C1: Notes
A2: GST rate | B2: 0.09 | C2: 9% for GST-registered businesses in Singapore. Set to 0 if you are not GST-registered.
A3: Approval limit | B3: 1000 | C3: POs with a total above this go to the approver first (used by the Make scenario).
A4: Approver email | B4: owner@example.com | C4: Who approves POs above the limit.
